<?xml version="1.0" encoding="utf-8" ?>
<dwsync>
<file name="5c17cbef1c14c18a0079672666e89d61.webp" server="rameystudentwork.com" local="133569219800512566" remote="133571887800000000" Dst="2" />
<file name="eyes_of_erra_logo.webp" server="rameystudentwork.com" local="133569194134888199" remote="133571887800000000" Dst="2" />
<file name="eyes_of_erra_text_logo.png" server="rameystudentwork.com" local="133569194146729018" remote="133571887800000000" Dst="2" />
<file name="Warframe_20180701143431.jpg" server="rameystudentwork.com" local="131949195440000000" remote="133571887800000000" Dst="2" />
<file name="eyes_of_erra_logo_200.jpg" server="rameystudentwork.com" local="133573240254554813" remote="133573255200000000" Dst="2" />
<file name="eyes_of_erra_text_logo_200.jpg" server="rameystudentwork.com" local="133573241112397643" remote="133573255200000000" Dst="2" />
<file name="volt_warframe_300.jpg" server="rameystudentwork.com" local="133573241973625341" remote="133573255200000000" Dst="2" />
<file name="eyes_of_erra_text_logo_300.jpg" server="rameystudentwork.com" local="133582208191364526" remote="133582209600000000" Dst="2" />
</dwsync>